LICENSE
README.md
setup.py
GUICaptures/GUICaptures.py
GUICaptures/__init__.py
GUICaptures.egg-info/PKG-INFO
GUICaptures.egg-info/SOURCES.txt
GUICaptures.egg-info/dependency_links.txt
GUICaptures.egg-info/requires.txt
GUICaptures.egg-info/top_level.txt