Metadata-Version: 1.1
Name: GUICaptures
Version: 0.1.1
Summary: Answering questions using NLTK and screen captures
Home-page: https://github.com/Sam-Nielsen-Dot/GUICaptures
Author: Sam Nielsen
Author-email: lenssimane@gmail.com
License: MIT
Platform: UNKNOWN
Classifier: Development Status :: 1 - Planning
Classifier: Intended Audience :: Healthcare Industry
Classifier: Environment :: Win32 (MS Windows)
Classifier: License :: OSI Approved :: MIT License
Classifier: Natural Language :: English
Classifier: Programming Language :: Python :: 2
Classifier: Programming Language :: Python :: 2.7
Classifier: Programming Language :: Python :: 3
Classifier: Programming Language :: Python :: 3.4
Classifier: Programming Language :: Python :: 3.5
